purecpp_libs_dev/__init__.py
purecpp_libs_dev/purecpp_libs_dev.cpython-39-x86_64-linux-gnu.so
purecpp_libs_dev-0.0.400.dist-info/METADATA
purecpp_libs_dev-0.0.400.dist-info/WHEEL
purecpp_libs_dev-0.0.400.dist-info/top_level.txt
purecpp_libs_dev-0.0.400.dist-info/RECORD
