Metadata-Version: 2.1
Name: purecpp_libs_dev
Version: 0.0.400
Summary: A set of methods for the PureAI framework(purecpp).
Home-page: https://github.com/pureai-ecosystem/purecpp
Author: PureAI
Author-email: contato@pureai.com.br
License: MIT
Classifier: Programming Language :: Python :: 3
Classifier: Operating System :: POSIX :: Linux
